fca/__init__.py
fca/__version__.py
fca/api_models.py
fca/association_rules.py
fca/base_models.py
fca/border_hasse.py
fca/get_lattice.py
fca/in_close.py
fca/plot/__init__.py
fca/plot/plot.py
fca/plot/tikz_tpl.py
fca/rca/__init__.py
fca/rca/cpop.py
fca/rca/models.py
fca/rca/p18n.py
fca/rca/rca.py
fca/rca/rca_mickael.py
fca/scripts/__init__.py
fca/scripts/export_utils.py
fca/scripts/fca_cli.py
fca/scripts/import_utils.py
fca/utils/__init__.py
fca/utils/utils.py
tests/__init__.py
tests/conftest.py
tests/test_association_rules.py
tests/test_in_close.py
tests/test_incremental.py
tests/test_incremental_by_pair.py
tests/test_incremental_delete.py
tests/test_rca.py
tests/utils.py
fca_algorithms-1.1.5.dist-info/LICENSE
fca_algorithms-1.1.5.dist-info/METADATA
fca_algorithms-1.1.5.dist-info/WHEEL
fca_algorithms-1.1.5.dist-info/entry_points.txt
fca_algorithms-1.1.5.dist-info/top_level.txt
fca_algorithms-1.1.5.dist-info/RECORD
