Metadata-Version: 2.1
Name: fca-algorithms
Version: 1.1.5
Summary: FCA basic algorithms
Home-page: https://gitlab.com/cps-phd-leutwyler-nicolas/rca_fca_general
Author: Ramshell
Author-email: ramshellcinox@gmail.com
License: CC By 4.0
Classifier: Programming Language :: Python :: 3
Classifier: Operating System :: OS Independent
Requires-Python: >=3.6
License-File: LICENSE
Requires-Dist: apyori >=1.1.2
Requires-Dist: networkx >=2.5
Requires-Dist: matplotlib >=3.3
Requires-Dist: fca-algorithms-cpp >=0.3.2
